jira2confluencegantt/__init__.py
jira2confluencegantt/__main__.py
jira2confluencegantt/cli.py
jira2confluencegantt/config.py
jira2confluencegantt/confluenceclient.py
jira2confluencegantt/jiraclient.py
jira2confluencegantt/report.py
jira2confluencegantt/task.py
jira2confluencegantt/templates/confluencechart.jinja2
jira2confluencegantt/templates/plantuml.jinja2
jira2confluencegantt/templates/plantumlmacro.jinja2
jira2confluence_gantt-0.3.3.dist-info/LICENSE
jira2confluence_gantt-0.3.3.dist-info/METADATA
jira2confluence_gantt-0.3.3.dist-info/WHEEL
jira2confluence_gantt-0.3.3.dist-info/entry_points.txt
jira2confluence_gantt-0.3.3.dist-info/RECORD
