Metadata-Version: 2.1
Name: jira2confluence-gantt
Version: 0.3.3
Summary: Gantt chart generator from Jira to Confluence
Home-page: https://github.com/cledouarec/jira2confluence-gantt
License: Apache-2.0
Keywords: project,management,visualization,gantt,jira,confluence,atlassian
Author: Christophe Le Douarec
Author-email: christophe.ledouarec@qorvo.com
Requires-Python: >=3.10,<4.0
Classifier: Environment :: Console
Classifier: License :: OSI Approved :: Apache Software License
Classifier: Operating System :: OS Independent
Classifier: Programming Language :: Python :: 3
Classifier: Programming Language :: Python :: 3.10
Classifier: Programming Language :: Python :: 3.11
Classifier: Programming Language :: Python :: 3.12
Classifier: Programming Language :: Python :: 3 :: Only
Classifier: Topic :: Office/Business :: Scheduling
Classifier: Topic :: Utilities
Requires-Dist: Jinja2 (>=3.1.3,<4.0.0)
Requires-Dist: PyYAML (>=6.0.1,<7.0.0)
Requires-Dist: anytree (>=2.12.1,<3.0.0)
Requires-Dist: atlassian-python-api (>=3.41.10,<4.0.0)
Requires-Dist: pydantic (>=2.6.3,<3.0.0)
Requires-Dist: pydantic-settings (>=2.2.1,<3.0.0)
Requires-Dist: python-dateutil (>=2.8.2,<3.0.0)
Project-URL: Repository, https://github.com/cledouarec/jira2confluence-gantt
